PythonBeginnerTopicsWithSampleCode/__init__.py
PythonBeginnerTopicsWithSampleCode/class_and_object.py
PythonBeginnerTopicsWithSampleCode/decorator.py
PythonBeginnerTopicsWithSampleCode/dictionary.py
PythonBeginnerTopicsWithSampleCode/functions.py
PythonBeginnerTopicsWithSampleCode/generator.py
PythonBeginnerTopicsWithSampleCode/interchangekeyvalue.py
PythonBeginnerTopicsWithSampleCode/lambda.py
PythonBeginnerTopicsWithSampleCode/lambda_sample.py
PythonBeginnerTopicsWithSampleCode/list_comprehension.py
PythonBeginnerTopicsWithSampleCode/magic_methods.py
PythonBeginnerTopicsWithSampleCode/oops.py
PythonBeginnerTopicsWithSampleCode/pass_cracker.py
PythonBeginnerTopicsWithSampleCode/python_string.py
PythonBeginnerTopicsWithSampleCode/scopes.py
PythonBeginnerTopicsWithSampleCode/slice.py
PythonBeginnerTopicsWithSampleCode/test.py
PythonBeginnerTopicsWithSampleCode/test_module.py
PythonBeginnerTopicsWithSampleCode/advanced_2024/__init__.py
PythonBeginnerTopicsWithSampleCode/advanced_2024/asynchronous.py
PythonBeginnerTopicsWithSampleCode/advanced_2024/map_filter_reduce.py
PythonBeginnerTopicsWithSampleCode/advanced_2024/multi_processing.py
PythonBeginnerTopicsWithSampleCode/advanced_2024/multi_thread.py
basic_codes/__init__.py
basic_codes/class_and_object.py
basic_codes/decorator.py
basic_codes/dictionary.py
basic_codes/functions.py
basic_codes/generator.py
basic_codes/interchangekeyvalue.py
basic_codes/lambda.py
basic_codes/lambda_sample.py
basic_codes/list_comprehension.py
basic_codes/magic_methods.py
basic_codes/oops.py
basic_codes/pass_cracker.py
basic_codes/python_string.py
basic_codes/scopes.py
basic_codes/slice.py
basic_codes/test.py
basic_codes/test_module.py
basic_codes/advanced_2024/__init__.py
basic_codes/advanced_2024/asynchronous.py
basic_codes/advanced_2024/map_filter_reduce.py
basic_codes/advanced_2024/multi_processing.py
basic_codes/advanced_2024/multi_thread.py
basic_codes-0.0.2.dist-info/LICENCE.TXT
basic_codes-0.0.2.dist-info/METADATA
basic_codes-0.0.2.dist-info/WHEEL
basic_codes-0.0.2.dist-info/top_level.txt
basic_codes-0.0.2.dist-info/RECORD
