Metadata-Version: 2.1
Name: basic_codes
Version: 0.0.2
Summary: A collection of basic Python topics with sample code for learning.
Author: Fawaskp
Author-email: <fawaskp1010@gmail.com>
License: MIT
Keywords: python,first package
Classifier: Development Status :: 3 - Alpha
Classifier: Intended Audience :: Education
Classifier: Programming Language :: Python :: 3
Classifier: Operating System :: MacOS :: MacOS X
Classifier: Operating System :: Microsoft :: Windows
License-File: LICENCE.TXT
